{"Haskell": [1, "/categories/haskell/", {"posts": [{"date": "05/31/2018", "isodate": "2018-05-31T11:22:08-04:00", "title": "Using LightGBM from Haskell", "url": "/posts/using-lightgbm-from-haskell/"}]}], "LightGBM": [1, "/categories/lightgbm/", {"posts": [{"date": "05/31/2018", "isodate": "2018-05-31T11:22:08-04:00", "title": "Using LightGBM from Haskell", "url": "/posts/using-lightgbm-from-haskell/"}]}], "Machine Learning": [1, "/categories/machine-learning/", {"posts": [{"date": "05/31/2018", "isodate": "2018-05-31T11:22:08-04:00", "title": "Using LightGBM from Haskell", "url": "/posts/using-lightgbm-from-haskell/"}]}], "blog": [1, "/categories/blog/", {"posts": [{"date": "04/14/2018", "isodate": "2018-04-14T16:20:56-04:00", "title": "A simple beginning", "url": "/posts/a-simple-beginning/"}]}], "boosting": [1, "/categories/boosting/", {"posts": [{"date": "05/31/2018", "isodate": "2018-05-31T11:22:08-04:00", "title": "Using LightGBM from Haskell", "url": "/posts/using-lightgbm-from-haskell/"}]}]}